tinytensor/__init__.py
tinytensor/math_utils.py
tinytensor/models.py
tinytensor/pipeline.py
tinytensor/postprocess.py
tinytensor/postprocessing/__init__.py
tinytensor/postprocessing/abstract.py
tinytensor/postprocessing/classification.py
tinytensor/postprocessing/regression.py
tinytensor/postprocessing/text_sequence.py
tinytensor/preprocess.py
tinytensor/preprocessing/__init__.py
tinytensor/preprocessing/abstract.py
tinytensor/preprocessing/tokenizer.py
tinytensor-0.1.0.dist-info/WHEEL
tinytensor-0.1.0.dist-info/METADATA
tinytensor-0.1.0.dist-info/RECORD
