Metadata-Version: 2.1
Name: tinytensor
Version: 0.1.0
Summary: tinytensor
License: MIT
Author: theblackcat102
Author-email: theblackcat102@github.com
Requires-Python: >=3.6,<4.0
Classifier: License :: OSI Approved :: MIT License
Classifier: Programming Language :: Python :: 3
Classifier: Programming Language :: Python :: 3.10
Classifier: Programming Language :: Python :: 3.6
Classifier: Programming Language :: Python :: 3.7
Classifier: Programming Language :: Python :: 3.8
Classifier: Programming Language :: Python :: 3.9
Requires-Dist: onnxruntime (>=1.10.0,<2.0.0)
Requires-Dist: tokenizers (>=0.11.0,<0.12.0)
